cakecmsutils/__init__.py
cakecmsutils/extendedcakecms.py
cakecmsutils-0.0.1.dist-info/LICENSE
cakecmsutils-0.0.1.dist-info/METADATA
cakecmsutils-0.0.1.dist-info/WHEEL
cakecmsutils-0.0.1.dist-info/top_level.txt
cakecmsutils-0.0.1.dist-info/RECORD
