Metadata-Version: 2.1
Name: cakecmsutils
Version: 0.0.1
Summary: Python scripts to interact with the CakeCMS API.
Home-page: https://github.com/fabian-thomas/cakecmsutils
Author: Fabian Thomas
Author-email: fabian@fabianthomas.de
License: UNKNOWN
Project-URL: Bug Tracker, https://github.com/fabian-thomas/cakecmsutils/issues
Platform: UNKNOWN
Classifier: Programming Language :: Python :: 3
Classifier: License :: OSI Approved :: MIT License
Classifier: Operating System :: OS Independent
License-File: LICENSE
